CHANGELOG.txt
LICENSE.txt
MANIFEST.in
README.md
setup.py
skywriter/__init__.py
skywriter.egg-info/PKG-INFO
skywriter.egg-info/SOURCES.txt
skywriter.egg-info/dependency_links.txt
skywriter.egg-info/requires.txt
skywriter.egg-info/top_level.txt